Workbook

Sheet Dashboard
A1: Meridian Retail Co. — Monthly FP&A Reporting Pack
A2: Auto-generated from the SQL pipeline (sales.db) — replaces a manual monthly Excel pull
A4: Latest Month Revenue | C4: MoM Growth % | E4: YoY Growth % | G4: FY2025 YTD Revenue | I4: Blended Gross Margin %
A5: =Data_Monthly!C27 -> 2795696.8 | C5: =Data_Monthly!F27 -> 0.24830417 | E5: =Data_Monthly!G27 -> 0.24641472 | G5: =Data_Monthly!I27 -> 18722119 | I5: =SUM(Data_Monthly!D4:D27)/SUM(Data_Monthly!C4:C27) -> 0.50355282
M26: Top 5 Customers by Revenue
M27: Customer | N27: Region | O27: Revenue
M28: =Top_Customers!B4 -> Customer 011 | N28: =Top_Customers!D4 -> North America | O28: =Top_Customers!E4 -> 1416014
M29: =Top_Customers!B5 -> Customer 026 | N29: =Top_Customers!D5 -> North America | O29: =Top_Customers!E5 -> 1228490.9
M30: =Top_Customers!B6 -> Customer 021 | N30: =Top_Customers!D6 -> North America | O30: =Top_Customers!E6 -> 1182150.4
M31: =Top_Customers!B7 -> Customer 056 | N31: =Top_Customers!D7 -> North America | O31: =Top_Customers!E7 -> 1177951.2
M32: =Top_Customers!B8 -> Customer 036 | N32: =Top_Customers!D8 -> North America | O32: =Top_Customers!E8 -> 1141319.5
A45: Headline insight: North America (+23.8% YoY) and Latin America (+28.9% YoY) are growing fast, but Greater Asia is down -37.8% YoY — that decline alone offsets most of the company's growth elsewhere, which is exactly the kind of finding this pipeline is built to surface automatically every month instead of waiting for a manual deep-dive.

Sheet Data_Monthly
A1: Monthly Revenue & Margin — Source: SQL export (monthly_kpis.csv) from sales.db
A3: Year-Month | B3: Transactions | C3: Net Revenue | D3: Gross Profit | E3: Gross Margin % | F3: MoM Growth % | G3: YoY Growth % | H3: 3-Mo Rolling Avg Revenue | I3: YTD Revenue
A4: 2024-01 | B4: 372 | C4: 1004033.1 | D4: 514305.14 | E4: =D4/C4 -> 0.51223921 | H4: =AVERAGE(C4:C4) -> 1004033.1 | I4: =C4 -> 1004033.1
A5: 2024-02 | B5: 387 | C5: 848108.49 | D5: 454347.49 | E5: =D5/C5 -> 0.5357186 | F5: =IFERROR(C5/C4-1,"") -> -0.15529831 | H5: =AVERAGE(C4:C5) -> 926070.81 | I5: =I4+C5 -> 1852141.6
A6: 2024-03 | B6: 503 | C6: 1502987.6 | D6: 740246.63 | E6: =D6/C6 -> 0.49251678 | F6: =IFERROR(C6/C5-1,"") -> 0.77216435 | H6: =AVERAGE(C4:C6) -> 1118376.4 | I6: =I5+C6 -> 3355129.3
A7: 2024-04 | B7: 489 | C7: 1625213.9 | D7: 803933.91 | E7: =D7/C7 -> 0.49466344 | F7: =IFERROR(C7/C6-1,"") -> 0.081322213 | H7: =AVERAGE(C5:C7) -> 1325436.7 | I7: =I6+C7 -> 4980343.2
A8: 2024-05 | B8: 565 | C8: 1609491 | D8: 798952.04 | E8: =D8/C8 -> 0.49640043 | F8: =IFERROR(C8/C7-1,"") -> -0.0096743388 | H8: =AVERAGE(C6:C8) -> 1579230.9 | I8: =I7+C8 -> 6589834.2
A9: 2024-06 | B9: 502 | C9: 1325122.7 | D9: 670308.71 | E9: =D9/C9 -> 0.50584652 | F9: =IFERROR(C9/C8-1,"") -> -0.17668215 | H9: =AVERAGE(C7:C9) -> 1519942.6 | I9: =I8+C9 -> 7914956.9
A10: 2024-07 | B10: 541 | C10: 1766492.7 | D10: 869298.67 | E10: =D10/C10 -> 0.49210432 | F10: =IFERROR(C10/C9-1,"") -> 0.33307856 | H10: =AVERAGE(C8:C10) -> 1567035.5 | I10: =I9+C10 -> 9681449.6
A11: 2024-08 | B11: 511 | C11: 1344137.8 | D11: 665792.82 | E11: =D11/C11 -> 0.49533077 | F11: =IFERROR(C11/C10-1,"") -> -0.23909233 | H11: =AVERAGE(C9:C11) -> 1478584.4 | I11: =I10+C11 -> 11025587
A12: 2024-09 | B12: 539 | C12: 1604749.7 | D12: 784629.72 | E12: =D12/C12 -> 0.48894211 | F12: =IFERROR(C12/C11-1,"") -> 0.19388778 | H12: =AVERAGE(C10:C12) -> 1571793.4 | I12: =I11+C12 -> 12630337
A13: 2024-10 | B13: 654 | C13: 1587225.6 | D13: 801412.59 | E13: =D13/C13 -> 0.50491411 | F13: =IFERROR(C13/C12-1,"") -> -0.010920164 | H13: =AVERAGE(C11:C13) -> 1512037.7 | I13: =I12+C13 -> 14217563
A14: 2024-11 | B14: 781 | C14: 2470827.8 | D14: 1220266.8 | E14: =D14/C14 -> 0.49386962 | F14: =IFERROR(C14/C13-1,"") -> 0.55669601 | H14: =AVERAGE(C12:C14) -> 1887601 | I14: =I13+C14 -> 16688390
A15: 2024-12 | B15: 803 | C15: 2242990.9 | D15: 1119678.9 | E15: =D15/C15 -> 0.49919011 | F15: =IFERROR(C15/C14-1,"") -> -0.092210758 | H15: =AVERAGE(C13:C15) -> 2100348.1 | I15: =I14+C15 -> 18931381
A16: 2025-01 | B16: 462 | C16: 1263567.4 | D16: 626837.4 | E16: =D16/C16 -> 0.49608545 | F16: =IFERROR(C16/C15-1,"") -> -0.43665958 | G16: =IFERROR(C16/C4-1,"") -> 0.25849173 | H16: =AVERAGE(C14:C16) -> 1992462 | I16: =C16 -> 1263567.4
A17: 2025-02 | B17: 464 | C17: 1173358.7 | D17: 608539.73 | E17: =D17/C17 -> 0.51863059 | F17: =IFERROR(C17/C16-1,"") -> -0.071392052 | G17: =IFERROR(C17/C5-1,"") -> 0.38350075 | H17: =AVERAGE(C15:C17) -> 1559972.3 | I17: =I16+C17 -> 2436926.1
A18: 2025-03 | B18: 529 | C18: 1072009.2 | D18: 571397.25 | E18: =D18/C18 -> 0.53301522 | F18: =IFERROR(C18/C17-1,"") -> -0.086375528 | G18: =IFERROR(C18/C6-1,"") -> -0.28674779 | H18: =AVERAGE(C16:C18) -> 1169645.1 | I18: =I17+C18 -> 3508935.4
A19: 2025-04 | B19: 565 | C19: 1364719.7 | D19: 724730.71 | E19: =D19/C19 -> 0.53104729 | F19: =IFERROR(C19/C18-1,"") -> 0.27304845 | G19: =IFERROR(C19/C7-1,"") -> -0.16028302 | H19: =AVERAGE(C17:C19) -> 1203362.6 | I19: =I18+C19 -> 4873655.1
A20: 2025-05 | B20: 549 | C20: 1446403.2 | D20: 721201.19 | E20: =D20/C20 -> 0.49861698 | F20: =IFERROR(C20/C19-1,"") -> 0.059853668 | G20: =IFERROR(C20/C8-1,"") -> -0.10132883 | H20: =AVERAGE(C18:C20) -> 1294377.4 | I20: =I19+C20 -> 6320058.3
A21: 2025-06 | B21: 570 | C21: 1274057.8 | D21: 668147.77 | E21: =D21/C21 -> 0.52442502 | F21: =IFERROR(C21/C20-1,"") -> -0.11915448 | G21: =IFERROR(C21/C9-1,"") -> -0.038536008 | H21: =AVERAGE(C19:C21) -> 1361726.9 | I21: =I20+C21 -> 7594116
A22: 2025-07 | B22: 530 | C22: 1373892.9 | D22: 695189.85 | E22: =D22/C22 -> 0.50600005 | F22: =IFERROR(C22/C21-1,"") -> 0.078359932 | G22: =IFERROR(C22/C10-1,"") -> -0.2222482 | H22: =AVERAGE(C20:C22) -> 1364784.6 | I22: =I21+C22 -> 8968008.9
A23: 2025-08 | B23: 620 | C23: 1420271.3 | D23: 733601.33 | E23: =D23/C23 -> 0.51652196 | F23: =IFERROR(C23/C22-1,"") -> 0.033756985 | G23: =IFERROR(C23/C11-1,"") -> 0.056641149 | H23: =AVERAGE(C21:C23) -> 1356074 | I23: =I22+C23 -> 10388280
A24: 2025-09 | B24: 555 | C24: 1369692.3 | D24: 692511.29 | E24: =D24/C24 -> 0.50559625 | F24: =IFERROR(C24/C23-1,"") -> -0.035612238 | G24: =IFERROR(C24/C12-1,"") -> -0.14647607 | H24: =AVERAGE(C22:C24) -> 1387952.2 | I24: =I23+C24 -> 11757973
A25: 2025-10 | B25: 698 | C25: 1928853.7 | D25: 973381.69 | E25: =D25/C25 -> 0.50464257 | F25: =IFERROR(C25/C24-1,"") -> 0.4082387 | G25: =IFERROR(C25/C13-1,"") -> 0.21523601 | H25: =AVERAGE(C23:C25) -> 1572939.1 | I25: =I24+C25 -> 13686826
A26: 2025-11 | B26: 847 | C26: 2239595.8 | D26: 1119549.8 | E26: =D26/C26 -> 0.49988923 | F26: =IFERROR(C26/C25-1,"") -> 0.16110198 | G26: =IFERROR(C26/C14-1,"") -> -0.093584796 | H26: =AVERAGE(C24:C26) -> 1846047.3 | I26: =I25+C26 -> 15926422
A27: 2025-12 | B27: 964 | C27: 2795696.8 | D27: 1382264.8 | E27: =D27/C27 -> 0.49442587 | F27: =IFERROR(C27/C26-1,"") -> 0.24830417 | G27: =IFERROR(C27/C15-1,"") -> 0.24641472 | H27: =AVERAGE(C25:C27) -> 2321382.1 | I27: =I26+C27 -> 18722119

Sheet Data_Regional
A1: Regional Revenue — Source: SQL export (regional_monthly.csv)
A3: Region | B3: FY2024 Revenue | C3: FY2025 Revenue | D3: YoY Growth % | E3: FY2025 Share of Total %
A4: APAC | B4: 2500409.1 | C4: 2573786.8 | D4: =C4/B4-1 -> 0.029346274 | E4: =C4/SUM($C$4:$C$8) -> 0.13747305
A5: Europe | B5: 4627658.6 | C5: 4548997.2 | D5: =C5/B5-1 -> -0.016998082 | E5: =C5/SUM($C$4:$C$8) -> 0.24297449
A6: Greater Asia | B6: 4982241.1 | C6: 3096550.1 | D6: =C6/B6-1 -> -0.37848248 | E6: =C6/SUM($C$4:$C$8) -> 0.16539528
A7: Latin America | B7: 1092050.7 | C7: 1408055.2 | D7: =C7/B7-1 -> 0.28936799 | E7: =C7/SUM($C$4:$C$8) -> 0.075208113
A8: North America | B8: 5729021.8 | C8: 7094729.5 | D8: =C8/B8-1 -> 0.23838409 | E8: =C8/SUM($C$4:$C$8) -> 0.37894907
A9: Total | B9: =SUM(B4:B8) -> 18931381 | C9: =SUM(C4:C8) -> 18722119 | D9: =C9/B9-1 -> -0.011053734
A12: Monthly Detail (for charting)
A13: Region | B13: Year-Month | C13: Net Revenue
A14: APAC | B14: 2024-01 | C14: 237539.04
A15: APAC | B15: 2024-02 | C15: 98057.68
A16: APAC | B16: 2024-03 | C16: 168158.49
A17: APAC | B17: 2024-04 | C17: 278890.29
A18: APAC | B18: 2024-05 | C18: 186600.84
A19: APAC | B19: 2024-06 | C19: 166801.79
A20: APAC | B20: 2024-07 | C20: 218357.76
A21: APAC | B21: 2024-08 | C21: 143763.49
A22: APAC | B22: 2024-09 | C22: 173792.91
A23: APAC | B23: 2024-10 | C23: 249582.48
A24: APAC | B24: 2024-11 | C24: 255814.64
A25: APAC | B25: 2024-12 | C25: 323049.71
... A133: North America | B133: 2025-12 | C133: 1222879.1

Sheet Data_Channel
A1: Channel Mix — Source: SQL export (channel_monthly.csv)
A3: Channel | B3: FY2024 Revenue | C3: FY2025 Revenue | D3: YoY Growth % | E3: FY2024 Share % | F3: FY2025 Share %
A4: Online | B4: 2706272.3 | C4: 3678634.3 | D4: =C4/B4-1 -> 0.35929937 | E4: =B4/SUM($B$4:$B$6) -> 0.14295166 | F4: =C4/SUM($C$4:$C$6) -> 0.196486
A5: Retail | B5: 2358210.1 | C5: 2034861.9 | D5: =C5/B5-1 -> -0.13711593 | E5: =B5/SUM($B$4:$B$6) -> 0.12456619 | F5: =C5/SUM($C$4:$C$6) -> 0.10868759
A6: Wholesale | B6: 13866899 | C6: 13008623 | D6: =C6/B6-1 -> -0.061893883 | E6: =B6/SUM($B$4:$B$6) -> 0.73248215 | F6: =C6/SUM($C$4:$C$6) -> 0.69482641

Sheet Data_Category
A1: Product Category Mix & Margin — Source: SQL export (category_monthly.csv)
A3: Category | B3: Net Revenue (FY24-25) | C3: Gross Profit | D3: Gross Margin % | E3: % of Total Revenue
A4: Accessories | B4: 4982577.3 | C4: 3221391.3 | D4: =C4/B4 -> 0.64653112 | E4: =B4/SUM($B$4:$B$7) -> 0.13232707
A5: Electronics | B5: 29190117 | C5: 12621397 | D5: =C5/B5 -> 0.43238596 | E5: =B5/SUM($B$4:$B$7) -> 0.77522983
A6: Services | B6: 1478231.4 | C6: 1296407.4 | D6: =C6/B6 -> 0.87699896 | E6: =B6/SUM($B$4:$B$7) -> 0.039258805
A7: Software | B7: 2002574.8 | C7: 1821330.8 | D7: =C7/B7 -> 0.90949452 | E7: =B7/SUM($B$4:$B$7) -> 0.053184294

Sheet Top_Customers
A1: Customer Revenue Ranking — Source: SQL export (customer_summary.csv)
A3: Rank | B3: Customer | C3: Segment | D3: Region | E3: Total Revenue | F3: Total Gross Profit | G3: Margin %
A4: =RANK(E4,$E$4:$E$63) -> 1 | B4: Customer 011 | C4: Consumer | D4: North America | E4: 1416014 | F4: 670372.97 | G4: =F4/E4 -> 0.47342257
A5: =RANK(E5,$E$4:$E$63) -> 2 | B5: Customer 026 | C5: SMB | D5: North America | E5: 1228490.9 | F5: 608419.93 | G5: =F5/E5 -> 0.49525797
A6: =RANK(E6,$E$4:$E$63) -> 3 | B6: Customer 021 | C6: Consumer | D6: North America | E6: 1182150.4 | F6: 580704.35 | G6: =F6/E6 -> 0.49122715
A7: =RANK(E7,$E$4:$E$63) -> 4 | B7: Customer 056 | C7: SMB | D7: North America | E7: 1177951.2 | F7: 589614.22 | G7: =F7/E7 -> 0.50054214
A8: =RANK(E8,$E$4:$E$63) -> 5 | B8: Customer 036 | C8: SMB | D8: North America | E8: 1141319.5 | F8: 564307.5 | G8: =F8/E8 -> 0.49443429
A9: =RANK(E9,$E$4:$E$63) -> 6 | B9: Customer 041 | C9: Consumer | D9: North America | E9: 1121545.8 | F9: 558127.81 | G9: =F9/E9 -> 0.49764156
A10: =RANK(E10,$E$4:$E$63) -> 7 | B10: Customer 001 | C10: Consumer | D10: North America | E10: 1085500.9 | F10: 557174.91 | G10: =F10/E10 -> 0.51328829
A11: =RANK(E11,$E$4:$E$63) -> 8 | B11: Customer 007 | C11: Consumer | D11: Europe | E11: 1072071.5 | F11: 509821.49 | G11: =F11/E11 -> 0.47554803
A12: =RANK(E12,$E$4:$E$63) -> 9 | B12: Customer 016 | C12: SMB | D12: North America | E12: 1055439.1 | F12: 541098.11 | G12: =F12/E12 -> 0.51267582
A13: =RANK(E13,$E$4:$E$63) -> 10 | B13: Customer 006 | C13: SMB | D13: North America | E13: 1031553.3 | F13: 516742.28 | G13: =F13/E13 -> 0.5009361
A14: =RANK(E14,$E$4:$E$63) -> 11 | B14: Customer 046 | C14: SMB | D14: North America | E14: 935710.31 | F14: 484951.31 | G14: =F14/E14 -> 0.51827078
A15: =RANK(E15,$E$4:$E$63) -> 12 | B15: Customer 017 | C15: Consumer | D15: Europe | E15: 900135.66 | F15: 433139.66 | G15: =F15/E15 -> 0.48119376
... A63: =RANK(E63,$E$4:$E$63) -> 60 | B63: Customer 040 | C63: Enterprise | D63: Latin America | E63: 122070.31 | F63: 66218.31 | G63: =F63/E63 -> 0.54246041
